creacli/__init__.py
creacli/__main__.py
creacli/ui.py
creacli-0.1.2.dist-info/METADATA
creacli-0.1.2.dist-info/RECORD
creacli-0.1.2.dist-info/WHEEL
creacli-0.1.2.dist-info/entry_points.txt
creacli-0.1.2.dist-info/top_level.txt
