Metadata-Version: 2.1
Name: creacli
Version: 0.1.2
Summary: Command line tool to interface with the Crea network
Home-page: http://library.creas.io/creacli
Author: Creativechain Foundation
Author-email: info@creativechain.org
Maintainer: Creativechain Foundation
Maintainer-email: info@creativechain.org
License: UNKNOWN
Download-URL: https://github.com/creativechain/creacli/tarball/0.1.2
Keywords: crea,library,api,rpc,cli
Platform: UNKNOWN
Classifier: License :: OSI Approved :: MIT License
Classifier: Operating System :: OS Independent
Classifier: Programming Language :: Python :: 3
Classifier: Development Status :: 3 - Alpha
Classifier: Intended Audience :: Developers
Requires-Dist: crea-lib (>=0.1.2)
Requires-Dist: prettytable (==0.7.2)
Requires-Dist: colorama (==0.3.6)
